{"project_name": "proyectoUNAM", "snapshot_number": 2, "services": [{"id": "0", "files": ["com.cocay.sicecd.model.Estado", "com.cocay.sicecd.model.Profesor", "com.cocay.sicecd.repo.EstadoRep", "com.cocay.sicecd.controller.ConsultaProfesorController", "com.cocay.sicecd.controller.ProfesoresController", "com.cocay.sicecd.controller.ModificarProfesor", "com.cocay.sicecd.controller.ModificarAsesores", "com.cocay.sicecd.step.ProcessorProfesor", "com.cocay.sicecd.model.Turno", "com.cocay.sicecd.model.Genero", "com.cocay.sicecd.model.Grado_profesor", "com.cocay.sicecd.repo.ProfesorRep", "com.cocay.sicecd.step.ReaderProfesor", "com.cocay.sicecd.repo.GeneroRep", "com.cocay.sicecd.repo.Grado_profesorRep", "com.cocay.sicecd.repo.TurnoRep", "com.cocay.sicecd.dto.ProfesorDto"], "new_classes": ["CertificadoRepRequestInterfaceImpl", "CertificadoRequestInterfaceImpl", "LoggingRequestInterfaceImpl", "GrupoRepRequestInterfaceImpl", "ProfesorRepHandleRequest", "ProfesorHandleRequest", "Grado_profesorHandleRequest", "GeneroHandleRequest", "TurnoHandleRequest"], "service_calls": [{"type": "synchronous", "protocol": "HTTP", "target": "findCertificado", "target_service": "2"}, {"type": "synchronous", "protocol": "HTTP", "target": "getPk_id_certificado", "target_service": "2"}, {"type": "synchronous", "protocol": "HTTP", "target": "setTrace", "target_service": "2"}, {"type": "synchronous", "protocol": "HTTP", "target": "setTrace", "target_service": "2"}, {"type": "synchronous", "protocol": "HTTP", "target": "setTrace", "target_service": "2"}, {"type": "synchronous", "protocol": "HTTP", "target": "findByIdAsesor", "target_service": "3"}], "entities": [], "dtos": ["CertificadoDTO", "CertificadoRepDTO", "LoggingDTO", "InscripcionDTO", "InscripcionRepDTO", "GrupoRepDTO", "CursoRepDTO", "Tipo_cursoRepDTO"], "interfaces": ["ProfesorInterface", "CertificadoRepDTOInterface", "CertificadoRepRequestInterface", "CertificadoRequestInterface", "LoggingDTOInterface", "LoggingRequestInterface", "GrupoRepDTOInterface", "GrupoRepRequestInterface"], "dependencies": {}, "independent": true}, {"id": "6", "files": ["com.cocay.sicecd.controller.ModificarCursos", "com.cocay.sicecd.repo.CursoRep", "com.cocay.sicecd.repo.Tipo_cursoRep", "com.cocay.sicecd.model.Curso", "com.cocay.sicecd.model.Tipo_curso", "com.cocay.sicecd.controller.ConsultaController", "com.cocay.sicecd.step.ProcessorCurso", "com.cocay.sicecd.controller.ConsultaCursoController", "com.cocay.sicecd.controller.CursosController", "com.cocay.sicecd.step.ReaderCurso", "com.cocay.sicecd.dto.CursoDto", "com.cocay.sicecd.config.ExcelConfig", "com.cocay.sicecd.step.CursoExcelRowMapper", "com.cocay.sicecd.step.LoggingCursoProcessor"], "new_classes": ["ProfesorRepRequestInterfaceImpl"], "service_calls": [{"type": "synchronous", "protocol": "HTTP", "target": "findByCompleteNameList", "target_service": "0"}], "entities": [], "dtos": ["ProfesorRepDTO", "GeneroRepDTO", "EstadoRepDTO", "Grado_profesorRepDTO", "TurnoRepDTO"], "interfaces": ["ProfesorRepDTOInterface", "ProfesorRepRequestInterface"], "dependencies": {"2": {"ModificarCursos": [["com.cocay.sicecd.service.Logging", "methodInvocation", "variableType"]], "Curso": [["com.cocay.sicecd.model.Certificado", "methodVariable", "databaseDependency"]], "CursosController": [["com.cocay.sicecd.service.Logging", "methodInvocation", "variableType"]]}, "0": {"ModificarCursos": [], "ConsultaController": []}, "1": {"ModificarCursos": [["com.cocay.sicecd.repo.InscripcionRep", "variableType"]]}, "3": {"ModificarCursos": [["com.cocay.sicecd.repo.GrupoRep", "variableType"]], "Curso": [["com.cocay.sicecd.model.Grupo", "variableType", "methodVariable", "databaseDependency"]], "ProcessorCurso": [["com.cocay.sicecd.repo.GrupoRep", "variableType"]]}}, "independent": false}, {"id": "2", "files": ["com.cocay.sicecd.model.Certificado", "com.cocay.sicecd.controller.DescargasController", "com.cocay.sicecd.controller.ClienteCertificadoController", "com.cocay.sicecd.controller.CertificadoMasivoController", "com.cocay.sicecd.service.Logging", "com.cocay.sicecd.repo.Log_sysRep", "com.cocay.sicecd.repo.Log_evento_sysRep", "com.cocay.sicecd.model.Log_sys", "com.cocay.sicecd.repo.Url_wsRep", "com.cocay.sicecd.model.Url_ws", "com.cocay.sicecd.model.Log_evento_sys", "com.cocay.sicecd.controller.AuditoriasController", "com.cocay.sicecd.repo.CertificadoRep", "com.cocay.sicecd.security.pdf.SeguridadPDF"], "new_classes": ["LoggingHandleRequest", "Usuario_sysRepRequestInterfaceImpl", "CertificadoRepHandleRequest", "CertificadoHandleRequest", "ProfesorRequestInterfaceImpl", "ProfesorRepRequestInterfaceImpl"], "service_calls": [{"type": "synchronous", "protocol": "HTTP", "target": "findById", "target_service": "7"}, {"type": "synchronous", "protocol": "HTTP", "target": "getPk_id_profesor", "target_service": "0"}, {"type": "synchronous", "protocol": "HTTP", "target": "getCorreo", "target_service": "0"}, {"type": "synchronous", "protocol": "HTTP", "target": "findByCorreo", "target_service": "0"}, {"type": "synchronous", "protocol": "HTTP", "target": "findByCorreo", "target_service": "0"}, {"type": "synchronous", "protocol": "HTTP", "target": "getPk_id_profesor", "target_service": "0"}], "entities": [], "dtos": ["Usuario_sysRepDTO", "Usuario_sysDTO", "ProfesorDTO", "ProfesorRepDTO"], "interfaces": ["Log_sysInterface", "Usuario_sysRepDTOInterface", "Usuario_sysRepRequestInterface", "CertificadoInterface", "ProfesorRequestInterface", "ProfesorDTOInterface", "ProfesorRepDTOInterface", "ProfesorRepRequestInterface"], "dependencies": {"0": {"Certificado": [], "DescargasController": [], "ClienteCertificadoController": [], "CertificadoMasivoController": []}, "6": {"Certificado": [["com.cocay.sicecd.model.Curso", "variableType", "methodVariable", "databaseDependency"]], "ClienteCertificadoController": [["com.cocay.sicecd.model.Curso", "methodInvocation", "methodVariable"], ["com.cocay.sicecd.repo.CursoRep", "methodInvocation", "variableType"]], "CertificadoMasivoController": [["com.cocay.sicecd.repo.CursoRep", "methodInvocation", "variableType"], ["com.cocay.sicecd.model.Curso", "methodInvocation"]]}, "3": {"Certificado": [["com.cocay.sicecd.model.Grupo", "variableType", "methodVariable", "databaseDependency"]], "ClienteCertificadoController": [["com.cocay.sicecd.model.Grupo", "methodInvocation", "methodVariable"], ["com.cocay.sicecd.repo.GrupoRep", "methodInvocation", "variableType"]], "CertificadoMasivoController": [["com.cocay.sicecd.model.Grupo", "methodInvocation"], ["com.cocay.sicecd.repo.GrupoRep", "variableType"]]}, "1": {"DescargasController": [["com.cocay.sicecd.repo.InscripcionRep", "variableType"]], "CertificadoMasivoController": [["com.cocay.sicecd.model.Inscripcion", "methodInvocation"]]}, "7": {"Logging": [], "Log_sys": []}}, "independent": false}, {"id": "4", "files": ["com.cocay.sicecd.service.WebService", "com.cocay.sicecd.repo.Url_ws_profesorRep", "com.cocay.sicecd.repo.Url_ws_cursoRep", "com.cocay.sicecd.repo.Url_ws_inscripcionRep", "com.cocay.sicecd.service.WebService.ReturnTypeOne", "com.cocay.sicecd.service.WebService.ReturnTypeTwo", "com.cocay.sicecd.service.WebService.ReturnTypeThree", "com.cocay.sicecd.model.Url_ws_profesor", "com.cocay.sicecd.model.Url_ws_curso", "com.cocay.sicecd.model.Url_ws_inscripcion"], "new_classes": ["ProfesorRepRequestInterfaceImpl", "ProfesorRequestInterfaceImpl"], "service_calls": [{"type": "synchronous", "protocol": "HTTP", "target": "findByCurp", "target_service": "0"}, {"type": "synchronous", "protocol": "HTTP", "target": "getPk_id_profesor", "target_service": "0"}], "entities": [], "dtos": ["ProfesorRepDTO"], "interfaces": ["ProfesorRepDTOInterface", "ProfesorRepRequestInterface", "ProfesorRequestInterface"], "dependencies": {"2": {"WebService": [["com.cocay.sicecd.service.Logging", "methodInvocation", "variableType"]]}, "6": {"WebService": [["com.cocay.sicecd.repo.CursoRep", "methodInvocation", "variableType"], ["com.cocay.sicecd.model.Curso", "methodInvocation"]]}, "3": {"WebService": [["com.cocay.sicecd.repo.GrupoRep", "methodInvocation", "variableType"], ["com.cocay.sicecd.model.Grupo", "methodInvocation"]]}, "0": {"WebService": []}, "1": {"WebService": [["com.cocay.sicecd.repo.InscripcionRep", "methodInvocation", "variableType"]]}}, "independent": false}, {"id": "1", "files": ["com.cocay.sicecd.model.Inscripcion", "com.cocay.sicecd.controller.ConsultaInscripcionController", "com.cocay.sicecd.step.ProcessorInscripcion", "com.cocay.sicecd.controller.InscripcionesController", "com.cocay.sicecd.controller.ModificarInscripcion", "com.cocay.sicecd.repo.InscripcionRep", "com.cocay.sicecd.dto.InscripcionDto"], "new_classes": ["ProfesorRepRequestInterfaceImpl", "ProfesorRequestInterfaceImpl", "Grado_profesorRequestInterfaceImpl", "GeneroRequestInterfaceImpl", "TurnoRequestInterfaceImpl"], "service_calls": [{"type": "synchronous", "protocol": "HTTP", "target": "findByName", "target_service": "0"}, {"type": "synchronous", "protocol": "HTTP", "target": "getFk_id_grado_profesor", "target_service": "0"}, {"type": "synchronous", "protocol": "HTTP", "target": "getPk_id_grado_profesor", "target_service": "0"}, {"type": "synchronous", "protocol": "HTTP", "target": "getPk_id_genero", "target_service": "0"}, {"type": "synchronous", "protocol": "HTTP", "target": "getPk_id_turno", "target_service": "0"}, {"type": "synchronous", "protocol": "HTTP", "target": "findByRfc", "target_service": "0"}, {"type": "synchronous", "protocol": "HTTP", "target": "findAll", "target_service": "0"}, {"type": "synchronous", "protocol": "HTTP", "target": "getRfc", "target_service": "0"}, {"type": "synchronous", "protocol": "HTTP", "target": "findAll", "target_service": "0"}, {"type": "synchronous", "protocol": "HTTP", "target": "getRfc", "target_service": "0"}], "entities": [], "dtos": ["ProfesorDTO", "ProfesorRepDTO", "GeneroRepDTO", "EstadoRepDTO", "Grado_profesorRepDTO", "TurnoRepDTO"], "interfaces": ["InscripcionInterface", "ProfesorRepDTOInterface", "ProfesorRepRequestInterface", "ProfesorRequestInterface", "Grado_profesorRequestInterface", "GeneroRequestInterface", "TurnoRequestInterface"], "dependencies": {"3": {"Inscripcion": [["com.cocay.sicecd.model.Grupo", "variableType", "methodVariable", "databaseDependency"]], "ConsultaInscripcionController": [["com.cocay.sicecd.repo.GrupoRep", "methodInvocation", "variableType"], ["com.cocay.sicecd.model.Grupo", "methodInvocation"]], "ProcessorInscripcion": [["com.cocay.sicecd.repo.GrupoRep", "methodInvocation", "variableType"]], "InscripcionesController": [["com.cocay.sicecd.repo.GrupoRep", "methodInvocation", "variableType"], ["com.cocay.sicecd.model.Grupo", "methodInvocation"]], "ModificarInscripcion": [["com.cocay.sicecd.repo.GrupoRep", "methodInvocation", "variableType"], ["com.cocay.sicecd.model.Grupo", "methodInvocation"]]}, "0": {"Inscripcion": [], "ConsultaInscripcionController": [], "ProcessorInscripcion": [], "InscripcionesController": [], "ModificarInscripcion": []}, "6": {"ConsultaInscripcionController": [["com.cocay.sicecd.repo.CursoRep", "methodInvocation", "variableType"], ["com.cocay.sicecd.model.Curso", "methodInvocation"]], "ProcessorInscripcion": [["com.cocay.sicecd.repo.CursoRep", "methodInvocation", "variableType"]], "ModificarInscripcion": [["com.cocay.sicecd.repo.CursoRep", "variableType"], ["com.cocay.sicecd.repo.Tipo_cursoRep", "variableType"]]}, "2": {"ConsultaInscripcionController": [["com.cocay.sicecd.repo.CertificadoRep", "methodInvocation", "variableType"], ["com.cocay.sicecd.model.Certificado", "methodInvocation"]], "InscripcionesController": [["com.cocay.sicecd.service.Logging", "methodInvocation", "variableType"]], "ModificarInscripcion": [["com.cocay.sicecd.service.Logging", "methodInvocation", "variableType"]]}}, "independent": false}, {"id": "5", "files": ["com.cocay.sicecd.config.BatchConfig", "com.cocay.sicecd.step.WriterCurso", "com.cocay.sicecd.repo.CursoBatchRep", "com.cocay.sicecd.step.WriterGrupo", "com.cocay.sicecd.repo.GrupoBatchRep", "com.cocay.sicecd.step.WriterInscripcion", "com.cocay.sicecd.repo.InscripcionBatchRep", "com.cocay.sicecd.repo.ProfesorBatchRep", "com.cocay.sicecd.step.WriterProfesor"], "new_classes": [], "service_calls": [], "entities": [], "dtos": ["ProcessorProfesorDTO", "ProfesorDTO"], "interfaces": [], "dependencies": {"3": {"BatchConfig": [["com.cocay.sicecd.step.ProcessorGrupo", "variableType"], ["com.cocay.sicecd.model.Grupo", "methodVariable"]]}, "6": {"BatchConfig": [["com.cocay.sicecd.step.ProcessorCurso", "variableType"], ["com.cocay.sicecd.model.Curso", "methodVariable"]]}, "1": {"BatchConfig": [["com.cocay.sicecd.step.ProcessorInscripcion", "variableType"], ["com.cocay.sicecd.model.Inscripcion", "methodVariable"]]}, "0": {"BatchConfig": []}}, "independent": false}, {"id": "3", "files": ["com.cocay.sicecd.model.Grupo", "com.cocay.sicecd.controller.BatchController", "com.cocay.sicecd.step.ProcessorGrupo", "com.cocay.sicecd.controller.GrupoController", "com.cocay.sicecd.controller.ModificarGrupos", "com.cocay.sicecd.repo.GrupoRep", "com.cocay.sicecd.controller.ConsultaGrupoController", "com.cocay.sicecd.step.ReaderGrupo", "com.cocay.sicecd.dto.GrupoDto"], "new_classes": ["GrupoRepHandleRequest", "ProfesorRepRequestInterfaceImpl", "ProfesorRequestInterfaceImpl"], "service_calls": [{"type": "synchronous", "protocol": "HTTP", "target": "loadAllProfesor", "target_service": "0"}, {"type": "synchronous", "protocol": "HTTP", "target": "getNombre", "target_service": "0"}, {"type": "synchronous", "protocol": "HTTP", "target": "findByRfc", "target_service": "0"}, {"type": "synchronous", "protocol": "HTTP", "target": "findAll", "target_service": "0"}, {"type": "synchronous", "protocol": "HTTP", "target": "getRfc", "target_service": "0"}, {"type": "synchronous", "protocol": "HTTP", "target": "getRfc", "target_service": "0"}, {"type": "synchronous", "protocol": "HTTP", "target": "findAll", "target_service": "0"}], "entities": [], "dtos": ["SendMailServiceDTO", "ProfesorDTO", "ProfesorRepDTO", "GeneroRepDTO", "EstadoRepDTO", "Grado_profesorRepDTO", "TurnoRepDTO"], "interfaces": ["GrupoInterface", "ProfesorRepDTOInterface", "ProfesorRepRequestInterface", "ProfesorRequestInterface"], "dependencies": {"6": {"Grupo": [["com.cocay.sicecd.model.Curso", "variableType", "methodVariable", "databaseDependency"]], "BatchController": [["com.cocay.sicecd.repo.CursoRep", "methodInvocation", "variableType"]], "ProcessorGrupo": [["com.cocay.sicecd.repo.CursoRep", "methodInvocation", "variableType"]], "GrupoController": [["com.cocay.sicecd.repo.CursoRep", "methodInvocation", "variableType"], ["com.cocay.sicecd.model.Curso", "methodInvocation"]], "ModificarGrupos": [["com.cocay.sicecd.model.Curso", "methodInvocation"], ["com.cocay.sicecd.repo.CursoRep", "methodInvocation", "variableType"], ["com.cocay.sicecd.repo.Tipo_cursoRep", "variableType"]], "GrupoRep": [["com.cocay.sicecd.model.Curso", "methodVariable"]], "ConsultaGrupoController": [["com.cocay.sicecd.model.Curso", "methodInvocation"]]}, "0": {"Grupo": [], "BatchController": [], "ProcessorGrupo": [], "GrupoController": [], "ModificarGrupos": []}, "2": {"Grupo": [["com.cocay.sicecd.model.Certificado", "methodVariable", "databaseDependency"]], "GrupoController": [["com.cocay.sicecd.service.Logging", "methodInvocation", "variableType"]], "ModificarGrupos": [["com.cocay.sicecd.service.Logging", "methodInvocation", "variableType"]]}, "1": {"Grupo": [["com.cocay.sicecd.model.Inscripcion", "methodVariable", "databaseDependency"]], "BatchController": [["com.cocay.sicecd.repo.InscripcionRep", "variableType"]], "ModificarGrupos": [["com.cocay.sicecd.repo.InscripcionRep", "variableType"]]}, "7": {"BatchController": []}}, "independent": false}, {"id": "8", "files": ["com.cocay.sicecd.webService.CargaBatchService", "com.cocay.sicecd.dto.ResponseGeneric", "com.cocay.sicecd.webService.CargaBatchServiceImpl", "com.cocay.sicecd.controller.ejemploServiceImpl", "com.cocay.sicecd.controller.ejemploService", "com.cocay.sicecd.webService.CorreoServiceImpl", "com.cocay.sicecd.webService.CorreoService", "com.cocay.sicecd.dao.AvisosCorreoDAO", "com.cocay.sicecd.dao.CargaBatchServiceDAO", "com.cocay.sicecd.dto.ErroresDTO", "com.cocay.sicecd.dto.FiltroCorreoDTO", "com.cocay.sicecd.dto.ResponseGenericPagination"], "new_classes": [], "service_calls": [], "entities": [], "dtos": ["SendMailServiceDTO", "ProfesorDtoDTO"], "interfaces": [], "dependencies": {"0": {"CorreoServiceImpl": [], "CorreoService": [], "AvisosCorreoDAO": [], "CargaBatchServiceDAO": [], "FiltroCorreoDTO": []}, "7": {"AvisosCorreoDAO": []}, "1": {"CargaBatchServiceDAO": [["com.cocay.sicecd.dto.InscripcionDto", "methodVariable"]], "FiltroCorreoDTO": [["com.cocay.sicecd.dto.InscripcionDto", "variableType", "methodVariable"]]}, "3": {"CargaBatchServiceDAO": [["com.cocay.sicecd.dto.GrupoDto", "methodVariable"]]}, "6": {"CargaBatchServiceDAO": [["com.cocay.sicecd.dto.CursoDto", "methodVariable"]], "FiltroCorreoDTO": [["com.cocay.sicecd.dto.CursoDto", "variableType", "methodVariable"]]}}, "independent": false}]}